CHANGELOG.txt
MANIFEST.in
README.in
README.txt
default.cfg
dev.cfg
eggbasket.kpf
sample-dev.cfg
setup.cfg
setup.py
start-eggbasket.py
test.cfg
EggBasket.egg-info/PKG-INFO
EggBasket.egg-info/SOURCES.txt
EggBasket.egg-info/dependency_links.txt
EggBasket.egg-info/entry_points.txt
EggBasket.egg-info/not-zip-safe
EggBasket.egg-info/paster_plugins.txt
EggBasket.egg-info/requires.txt
EggBasket.egg-info/top_level.txt
doc/index.html
doc/rest.css
doc/api/epydoc.css
doc/api/index.html
doc/api/private/__builtin__.dict-class.html
doc/api/private/__builtin__.object-class.html
doc/api/private/__builtin__.type-class.html
doc/api/private/eggbasket-module.html
doc/api/private/eggbasket.config-module.html
doc/api/private/eggbasket.odict-module.html
doc/api/private/eggbasket.odict.Items-class.html
doc/api/private/eggbasket.odict.Keys-class.html
doc/api/private/eggbasket.odict.OrderedDict-class.html
doc/api/private/eggbasket.odict.SequenceOrderedDict-class.html
doc/api/private/eggbasket.odict.Values-class.html
doc/api/private/eggbasket.release-module.html
doc/api/private/eggbasket.rest-module.html
doc/api/private/eggbasket.rest.Warnings-class.html
doc/api/private/eggbasket.templates-module.html
doc/api/private/eggbasket.tests-module.html
doc/api/private/epydoc.css
doc/api/private/frames.html
doc/api/private/help.html
doc/api/private/index.html
doc/api/private/indices.html
doc/api/private/toc-eggbasket-module.html
doc/api/private/toc-eggbasket.config-module.html
doc/api/private/toc-eggbasket.odict-module.html
doc/api/private/toc-eggbasket.release-module.html
doc/api/private/toc-eggbasket.rest-module.html
doc/api/private/toc-eggbasket.templates-module.html
doc/api/private/toc-eggbasket.tests-module.html
doc/api/private/toc-everything.html
doc/api/private/toc.html
doc/api/private/trees.html
doc/api/public/__builtin__.dict-class.html
doc/api/public/__builtin__.object-class.html
doc/api/public/__builtin__.type-class.html
doc/api/public/eggbasket-module.html
doc/api/public/eggbasket.config-module.html
doc/api/public/eggbasket.odict-module.html
doc/api/public/eggbasket.odict.OrderedDict-class.html
doc/api/public/eggbasket.odict.SequenceOrderedDict-class.html
doc/api/public/eggbasket.release-module.html
doc/api/public/eggbasket.rest-module.html
