Metadata-Version: 1.0
Name: EggBasket
Version: 0.6.1b
Summary: A simple, lightweight Python Package Index (aka Cheeseshop) clone.
Home-page: http://chrisarndt.de/projects/eggbasket/
Author: Christopher Arndt
Author-email: chris@chrisarndt.de
License: MIT License, Zope Public License (rest.py), BSD License (odict.py)
Download-URL: http://cheeseshop.python.org/pypi/EggBasket
Keywords: turbogears.app
Platform: UNKNOWN
Classifier: Development Status :: 4 - Beta
Classifier: Operating System :: OS Independent
Classifier: Programming Language :: Python
Classifier: Topic :: Software Development :: Libraries :: Python Modules
Classifier: Framework :: TurboGears
Classifier: Framework :: TurboGears :: Applications
